[{
		"id":"video01",
		"imgurl":"public/images/video01.jpg",
		"name":"小微企业最新优惠政策",
		"teacher":"钟宜静",
		"time":"5分钟",
		"courseware":true,
		"download":{
			"size":"5.5M",
    		"type":"视频",
    		"num":"1000"
		},
		"dec":"了解最新政策、了解最新政策、了解最新政策、了解最新政策、了解最新政策、了解最新政策、了解最新政策、了解最新政策"
	},{
		"id":"video02",
		"imgurl":"public/images/video02.jpg",
		"name":"个人所得税",
		"teacher":"钟宜静",
		"time":"5分钟",
		"courseware":true,
		"download":{
			"size":"5.5M",
    		"type":"视频",
    		"num":"1000"
		},
		"dec":"了解最新政策"
	},{
		"id":"video03",
		"imgurl":"public/images/video03.jpg",
		"name":"增值说纳税申报辅导",
		"teacher":"钟宜静",
		"time":"5分钟",
		"courseware":true,
		"download":{
			"size":"5.5M",
    		"type":"视频",
    		"num":"1000"
		},
		"dec":"了解最新政策"
	},{
		"id":"video01",
		"imgurl":"public/images/video01.jpg",
		"name":"小微企业最新优惠政策",
		"teacher":"钟宜静",
		"time":"5分钟",
		"courseware":true,
		"download":{
			"size":"5.5M",
    		"type":"视频",
    		"num":"1000"
		},
		"dec":"了解最新政策"
	},{
		"id":"video02",
		"imgurl":"public/images/video02.jpg",
		"name":"个人所得税",
		"teacher":"钟宜静",
		"time":"5分钟",
		"courseware":true,
		"download":{
			"size":"5.5M",
    		"type":"视频",
    		"num":"1000"
		},
		"dec":"了解最新政策"
	},{
		"id":"video03",
		"imgurl":"public/images/video03.jpg",
		"name":"增值说纳税申报辅导",
		"teacher":"钟宜静",
		"time":"5分钟",
		"courseware":true,
		"download":{
			"size":"5.5M",
    		"type":"视频",
    		"num":"1000"
		},
		"dec":"了解最新政策"
	}
	
]